napari_stitcher/__init__.py
napari_stitcher/_mosaic_widget.py
napari_stitcher/_reader.py
napari_stitcher/_sample_data.py
napari_stitcher/_stitcher_widget.py
napari_stitcher/_utils.py
napari_stitcher/_version.py
napari_stitcher/_writer.py
napari_stitcher/napari.yaml
napari_stitcher/viewer_utils.py
napari_stitcher/_tests/__init__.py
napari_stitcher/_tests/test_mosaic_widget.py
napari_stitcher/_tests/test_reader.py
napari_stitcher/_tests/test_stitcher_widget.py
napari_stitcher/_tests/test_viewer_utils.py
napari_stitcher/_tests/test_writer.py
napari_stitcher-0.1.2.dist-info/licenses/LICENSE
napari_stitcher-0.1.2.dist-info/METADATA
napari_stitcher-0.1.2.dist-info/WHEEL
napari_stitcher-0.1.2.dist-info/entry_points.txt
napari_stitcher-0.1.2.dist-info/top_level.txt
napari_stitcher-0.1.2.dist-info/RECORD
