Metadata-Version: 2.4
Name: napari-stitcher
Version: 0.1.2
Summary: Stitch napari image layers in 2-3D+t
Author: Marvin Albert
Author-email: marvin.albert@gmail.com
License: BSD-3-Clause
Project-URL: Bug Tracker, https://github.com/multiview-stitcher/napari-stitcher/issues
Project-URL: Documentation, https://multiview-stitcher.github.io/napari-stitcher/
Project-URL: Source Code, https://github.com/multiview-stitcher/napari-stitcher
Project-URL: User Support, https://github.com/multiview-stitcher/napari-stitcher/issues
Classifier: Development Status :: 2 - Pre-Alpha
Classifier: Framework :: napari
Classifier: Intended Audience :: Developers
Classifier: License :: OSI Approved :: BSD License
Classifier: Operating System :: OS Independent
Classifier: Programming Language :: Python
Classifier: Programming Language :: Python :: 3
Classifier: Programming Language :: Python :: 3 :: Only
Classifier: Programming Language :: Python :: 3.10
Classifier: Programming Language :: Python :: 3.11
Classifier: Programming Language :: Python :: 3.12
Classifier: Topic :: Scientific/Engineering :: Image Processing
Requires-Python: >=3.10
License-File: LICENSE
Requires-Dist: dask
Requires-Dist: magicgui
Requires-Dist: multiscale_spatial_image
Requires-Dist: multiview-stitcher>=0.1.24
Requires-Dist: napari
Requires-Dist: numpy>=1.18
Requires-Dist: qtpy
Requires-Dist: spatial_image
Requires-Dist: tifffile>=2022.7.28
Requires-Dist: tqdm
Requires-Dist: xarray
Provides-Extra: testing-no-gui
Requires-Dist: tox; extra == "testing-no-gui"
Requires-Dist: multiview-stitcher[czi]>=0.1.24; extra == "testing-no-gui"
Requires-Dist: pytest; extra == "testing-no-gui"
Requires-Dist: pytest-cov; extra == "testing-no-gui"
Requires-Dist: pytest-qt; extra == "testing-no-gui"
Provides-Extra: testing
Requires-Dist: tox; extra == "testing"
Requires-Dist: multiview-stitcher[czi]>=0.1.24; extra == "testing"
Requires-Dist: pytest; extra == "testing"
Requires-Dist: pytest-cov; extra == "testing"
Requires-Dist: pytest-qt; extra == "testing"
Requires-Dist: napari; extra == "testing"
Requires-Dist: pyqt5; extra == "testing"
Dynamic: license-file
